YibubuDajianWuLianwangXitong/README.md
YibubuDajianWuLianwangXitong/__init__.py
YibubuDajianWuLianwangXitong/__main__.py
YibubuDajianWuLianwangXitong/file.epub
YibubuDajianWuLianwangXitong/index.html
YibubuDajianWuLianwangXitong/css/__init__.py
YibubuDajianWuLianwangXitong/css/annotations.css
YibubuDajianWuLianwangXitong/css/main.css
YibubuDajianWuLianwangXitong/css/normalize.css
YibubuDajianWuLianwangXitong/css/popup.css
YibubuDajianWuLianwangXitong/font/__init__.py
YibubuDajianWuLianwangXitong/font/fontello.eot
YibubuDajianWuLianwangXitong/font/fontello.svg
YibubuDajianWuLianwangXitong/font/fontello.ttf
YibubuDajianWuLianwangXitong/font/fontello.woff
YibubuDajianWuLianwangXitong/img/__init__.py
YibubuDajianWuLianwangXitong/img/annotator-glyph-sprite.png
YibubuDajianWuLianwangXitong/img/annotator-icon-sprite.png
YibubuDajianWuLianwangXitong/img/apple-touch-icon.png
YibubuDajianWuLianwangXitong/img/cancelfullscreen.png
YibubuDajianWuLianwangXitong/img/close.png
YibubuDajianWuLianwangXitong/img/fullscreen.png
YibubuDajianWuLianwangXitong/img/loader.gif
YibubuDajianWuLianwangXitong/img/menu-icon.png
YibubuDajianWuLianwangXitong/img/save.png
YibubuDajianWuLianwangXitong/img/saved.png
YibubuDajianWuLianwangXitong/img/settings-s.png
YibubuDajianWuLianwangXitong/img/settings.png
YibubuDajianWuLianwangXitong/img/star.png
YibubuDajianWuLianwangXitong/js/__init__.py
YibubuDajianWuLianwangXitong/js/epub.js
YibubuDajianWuLianwangXitong/js/epub.min.js
YibubuDajianWuLianwangXitong/js/epub.min.map
YibubuDajianWuLianwangXitong/js/hooks.min.js
YibubuDajianWuLianwangXitong/js/hooks.min.map
YibubuDajianWuLianwangXitong/js/reader.js
YibubuDajianWuLianwangXitong/js/reader.js.map
YibubuDajianWuLianwangXitong/js/reader.min.js
YibubuDajianWuLianwangXitong/js/reader.min.map
YibubuDajianWuLianwangXitong/js/hooks/__init__.py
YibubuDajianWuLianwangXitong/js/hooks/extensions/__init__.py
YibubuDajianWuLianwangXitong/js/hooks/extensions/highlight.js
yibubu_dajian_wu_lianwang_xitong-2024.3.2.0.dist-info/METADATA
yibubu_dajian_wu_lianwang_xitong-2024.3.2.0.dist-info/WHEEL
yibubu_dajian_wu_lianwang_xitong-2024.3.2.0.dist-info/entry_points.txt
yibubu_dajian_wu_lianwang_xitong-2024.3.2.0.dist-info/top_level.txt
yibubu_dajian_wu_lianwang_xitong-2024.3.2.0.dist-info/RECORD
